{
	"info": {
		"_postman_id": "964ecef1-445e-41a1-babf-b6001af626b9",
		"name": "Proyecto-2-Gym-App",
		"schema": "https://schema.getpostman.com/json/collection/v2.1.0/collection.json",
		"_exporter_id": "24964205"
	},
	"item": [
		{
			"name": "get login - no-registrado",
			"protocolProfileBehavior": {
				"disableBodyPruning": true
			},
			"request": {
				"method": "GET",
				"header": [],
				"body": {
					"mode": "raw",
					"raw": "{\n    \"email\": \"random@mail.com\",\n    \"password\": \"1234567890\"\n}",
					"options": {
						"raw": {
							"language": "json"
						}
					}
				},
				"url": {
					"raw": "http://localhost:8080/login",
					"protocol": "http",
					"host": [
						"localhost"
					],
					"port": "8080",
					"path": [
						"login"
					]
				}
			},
			"response": []
		},
		{
			"name": "get login - worker1",
			"protocolProfileBehavior": {
				"disableBodyPruning": true
			},
			"request": {
				"method": "GET",
				"header": [],
				"body": {
					"mode": "raw",
					"raw": "{\n    \"email\": \"worker2@mail.com\",\n    \"password\": \"1234567890\"\n}",
					"options": {
						"raw": {
							"language": "json"
						}
					}
				},
				"url": {
					"raw": "http://localhost:8080/login",
					"protocol": "http",
					"host": [
						"localhost"
					],
					"port": "8080",
					"path": [
						"login"
					]
				}
			},
			"response": []
		},
		{
			"name": "get login - worker2",
			"protocolProfileBehavior": {
				"disableBodyPruning": true
			},
			"request": {
				"method": "GET",
				"header": [],
				"body": {
					"mode": "raw",
					"raw": "{\n    \"email\": \"worker2@mail.com\",\n    \"password\": \"1234567890\"\n}",
					"options": {
						"raw": {
							"language": "json"
						}
					}
				},
				"url": {
					"raw": "http://localhost:8080/login",
					"protocol": "http",
					"host": [
						"localhost"
					],
					"port": "8080",
					"path": [
						"login"
					]
				}
			},
			"response": []
		},
		{
			"name": "get login - admin",
			"protocolProfileBehavior": {
				"disableBodyPruning": true
			},
			"request": {
				"method": "GET",
				"header": [],
				"body": {
					"mode": "raw",
					"raw": "{\n    \"email\": \"administrator@mail.com\",\n    \"password\": \"1234567890\"\n}",
					"options": {
						"raw": {
							"language": "json"
						}
					}
				},
				"url": {
					"raw": "http://localhost:8080/login",
					"protocol": "http",
					"host": [
						"localhost"
					],
					"port": "8080",
					"path": [
						"login"
					]
				}
			},
			"response": []
		},
		{
			"name": "get exercises - sin filtros - sin login",
			"protocolProfileBehavior": {
				"disableBodyPruning": true
			},
			"request": {
				"method": "GET",
				"header": [],
				"body": {
					"mode": "raw",
					"raw": "",
					"options": {
						"raw": {
							"language": "json"
						}
					}
				},
				"url": {
					"raw": "http://localhost:8080/exercises",
					"protocol": "http",
					"host": [
						"localhost"
					],
					"port": "8080",
					"path": [
						"exercises"
					]
				}
			},
			"response": []
		},
		{
			"name": "get exercises - sin filtros - login worker2",
			"protocolProfileBehavior": {
				"disableBodyPruning": true
			},
			"request": {
				"method": "GET",
				"header": [
					{
						"key": "Authorization",
						"value": "Bearer eyJhbGciOiJIUzI1NiIsInR5cCI6IkpXVCJ9.eyJpZFVzZXIiOjMsImlhdCI6MTY3MzM4ODkyMCwiZXhwIjoxNjczNDc1MzIwfQ.sjUvg2JZVr4q9qUoWNQknSrqaAqqCVNiZUrF_fD5BLY",
						"type": "text"
					}
				],
				"body": {
					"mode": "raw",
					"raw": "",
					"options": {
						"raw": {
							"language": "json"
						}
					}
				},
				"url": {
					"raw": "http://localhost:8080/exercises",
					"protocol": "http",
					"host": [
						"localhost"
					],
					"port": "8080",
					"path": [
						"exercises"
					]
				}
			},
			"response": []
		},
		{
			"name": "get exercise (1) details - login worker2",
			"request": {
				"method": "GET",
				"header": [
					{
						"key": "Authorization",
						"value": "Bearer eyJhbGciOiJIUzI1NiIsInR5cCI6IkpXVCJ9.eyJpZFVzZXIiOjMsImlhdCI6MTY3MzM4ODkyMCwiZXhwIjoxNjczNDc1MzIwfQ.sjUvg2JZVr4q9qUoWNQknSrqaAqqCVNiZUrF_fD5BLY",
						"type": "text"
					}
				],
				"url": {
					"raw": "http://localhost:8080/exercises/1",
					"protocol": "http",
					"host": [
						"localhost"
					],
					"port": "8080",
					"path": [
						"exercises",
						"1"
					]
				}
			},
			"response": []
		},
		{
			"name": "get exercise - con filtros (1) -  login worker2",
			"protocolProfileBehavior": {
				"disableBodyPruning": true
			},
			"request": {
				"method": "GET",
				"header": [
					{
						"key": "Authorization",
						"value": "Bearer eyJhbGciOiJIUzI1NiIsInR5cCI6IkpXVCJ9.eyJpZFVzZXIiOjMsImlhdCI6MTY3MzM4ODkyMCwiZXhwIjoxNjczNDc1MzIwfQ.sjUvg2JZVr4q9qUoWNQknSrqaAqqCVNiZUrF_fD5BLY",
						"type": "text"
					}
				],
				"body": {
					"mode": "raw",
					"raw": "",
					"options": {
						"raw": {
							"language": "json"
						}
					}
				},
				"url": {
					"raw": "http://localhost:8080/exercises?muscles=biceps",
					"protocol": "http",
					"host": [
						"localhost"
					],
					"port": "8080",
					"path": [
						"exercises"
					],
					"query": [
						{
							"key": "muscles",
							"value": "biceps"
						}
					]
				}
			},
			"response": []
		},
		{
			"name": "get exercise - con filtros (2) - login worker2",
			"protocolProfileBehavior": {
				"disableBodyPruning": true
			},
			"request": {
				"method": "GET",
				"header": [
					{
						"key": "Authorization",
						"value": "Bearer eyJhbGciOiJIUzI1NiIsInR5cCI6IkpXVCJ9.eyJpZFVzZXIiOjMsImlhdCI6MTY3MzM4ODkyMCwiZXhwIjoxNjczNDc1MzIwfQ.sjUvg2JZVr4q9qUoWNQknSrqaAqqCVNiZUrF_fD5BLY",
						"type": "text"
					}
				],
				"body": {
					"mode": "raw",
					"raw": "",
					"options": {
						"raw": {
							"language": "json"
						}
					}
				},
				"url": {
					"raw": "http://localhost:8080/exercises?muscles=biceps&typology=peso auxiliar",
					"protocol": "http",
					"host": [
						"localhost"
					],
					"port": "8080",
					"path": [
						"exercises"
					],
					"query": [
						{
							"key": "muscles",
							"value": "biceps"
						},
						{
							"key": "typology",
							"value": "peso auxiliar"
						}
					]
				}
			},
			"response": []
		},
		{
			"name": "get favs - worker1 (sin favs)",
			"protocolProfileBehavior": {
				"disableBodyPruning": true
			},
			"request": {
				"method": "GET",
				"header": [],
				"body": {
					"mode": "raw",
					"raw": "",
					"options": {
						"raw": {
							"language": "json"
						}
					}
				},
				"url": {
					"raw": "http://localhost:8080/favorites/1",
					"protocol": "http",
					"host": [
						"localhost"
					],
					"port": "8080",
					"path": [
						"favorites",
						"1"
					]
				}
			},
			"response": []
		},
		{
			"name": "get favs - worker2",
			"protocolProfileBehavior": {
				"disableBodyPruning": true
			},
			"request": {
				"method": "GET",
				"header": [
					{
						"key": "Authorization",
						"value": "Bearer eyJhbGciOiJIUzI1NiIsInR5cCI6IkpXVCJ9.eyJpZFVzZXIiOjMsImlhdCI6MTY3MzM4ODkyMCwiZXhwIjoxNjczNDc1MzIwfQ.sjUvg2JZVr4q9qUoWNQknSrqaAqqCVNiZUrF_fD5BLY",
						"type": "text"
					}
				],
				"body": {
					"mode": "raw",
					"raw": "",
					"options": {
						"raw": {
							"language": "json"
						}
					}
				},
				"url": {
					"raw": "http://localhost:8080/favorites/2",
					"protocol": "http",
					"host": [
						"localhost"
					],
					"port": "8080",
					"path": [
						"favorites",
						"2"
					]
				}
			},
			"response": []
		},
		{
			"name": "get favs - usuario inexistente",
			"protocolProfileBehavior": {
				"disableBodyPruning": true
			},
			"request": {
				"method": "GET",
				"header": [],
				"body": {
					"mode": "raw",
					"raw": "",
					"options": {
						"raw": {
							"language": "json"
						}
					}
				},
				"url": {
					"raw": "http://localhost:8080/favorites/150",
					"protocol": "http",
					"host": [
						"localhost"
					],
					"port": "8080",
					"path": [
						"favorites",
						"150"
					]
				}
			},
			"response": []
		},
		{
			"name": "post newExercise - correr",
			"request": {
				"auth": {
					"type": "noauth"
				},
				"method": "POST",
				"header": [
					{
						"key": "Authorization",
						"value": "Bearer eyJhbGciOiJIUzI1NiIsInR5cCI6IkpXVCJ9.eyJpZFVzZXIiOjEsImlhdCI6MTY3MzM4OTcxNSwiZXhwIjoxNjczNDc2MTE1fQ.TjE7Iy4o9lQ6i_nNs9Lpu0m-g1yG9LkzsbnglAl6Yx4",
						"type": "text"
					}
				],
				"body": {
					"mode": "formdata",
					"formdata": [
						{
							"key": "name",
							"value": "correr",
							"type": "text"
						},
						{
							"key": "description",
							"value": "caminar rapido",
							"type": "text"
						},
						{
							"key": "typology",
							"value": "cardio",
							"type": "text"
						},
						{
							"key": "muscles",
							"value": "piernas",
							"type": "text"
						},
						{
							"key": "picture",
							"type": "file",
							"src": "/home/gonzalo/estudios/HAB-bootcamp/proyectos/proyecto-02/gym-app/ProyectoGym/postman/correr.jpeg"
						}
					]
				},
				"url": {
					"raw": "http://localhost:8080/newExercise",
					"protocol": "http",
					"host": [
						"localhost"
					],
					"port": "8080",
					"path": [
						"newExercise"
					]
				}
			},
			"response": []
		},
		{
			"name": "put editExercise - correr => trotar",
			"request": {
				"auth": {
					"type": "noauth"
				},
				"method": "PUT",
				"header": [
					{
						"key": "Authorization",
						"value": "Bearer eyJhbGciOiJIUzI1NiIsInR5cCI6IkpXVCJ9.eyJpZFVzZXIiOjEsImlhdCI6MTY3MzM4OTcxNSwiZXhwIjoxNjczNDc2MTE1fQ.TjE7Iy4o9lQ6i_nNs9Lpu0m-g1yG9LkzsbnglAl6Yx4",
						"type": "text"
					}
				],
				"body": {
					"mode": "formdata",
					"formdata": [
						{
							"key": "name",
							"value": "trotar",
							"type": "text"
						},
						{
							"key": "description",
							"value": "correr lento",
							"type": "text"
						},
						{
							"key": "typology",
							"value": "cardio",
							"type": "text"
						},
						{
							"key": "muscles",
							"value": "piernas",
							"type": "text"
						},
						{
							"key": "picture",
							"type": "file",
							"src": "/home/gonzalo/estudios/HAB-bootcamp/proyectos/proyecto-02/gym-app/ProyectoGym/postman/correr.jpeg"
						}
					]
				},
				"url": {
					"raw": "http://localhost:8080/newExercise",
					"protocol": "http",
					"host": [
						"localhost"
					],
					"port": "8080",
					"path": [
						"newExercise"
					]
				}
			},
			"response": []
		},
		{
			"name": "post like/dislike worker2 exercise1",
			"request": {
				"auth": {
					"type": "noauth"
				},
				"method": "POST",
				"header": [
					{
						"key": "Authorization",
						"value": "Bearer eyJhbGciOiJIUzI1NiIsInR5cCI6IkpXVCJ9.eyJpZFVzZXIiOjMsImlhdCI6MTY3MzM4ODkyMCwiZXhwIjoxNjczNDc1MzIwfQ.sjUvg2JZVr4q9qUoWNQknSrqaAqqCVNiZUrF_fD5BLY",
						"type": "text"
					}
				],
				"url": {
					"raw": "http://localhost:8080/exercises/1/like",
					"protocol": "http",
					"host": [
						"localhost"
					],
					"port": "8080",
					"path": [
						"exercises",
						"1",
						"like"
					]
				}
			},
			"response": []
		},
		{
			"name": "post fav/unfav worker2 exercise1",
			"request": {
				"auth": {
					"type": "noauth"
				},
				"method": "POST",
				"header": [
					{
						"key": "Authorization",
						"value": "Bearer eyJhbGciOiJIUzI1NiIsInR5cCI6IkpXVCJ9.eyJpZFVzZXIiOjMsImlhdCI6MTY3MzM4ODkyMCwiZXhwIjoxNjczNDc1MzIwfQ.sjUvg2JZVr4q9qUoWNQknSrqaAqqCVNiZUrF_fD5BLY",
						"type": "text"
					}
				],
				"url": {
					"raw": "http://localhost:8080/exercises/4/fav",
					"protocol": "http",
					"host": [
						"localhost"
					],
					"port": "8080",
					"path": [
						"exercises",
						"4",
						"fav"
					]
				}
			},
			"response": []
		},
		{
			"name": "delete exercise (1)",
			"request": {
				"method": "DELETE",
				"header": [
					{
						"key": "Authorization",
						"value": "Bearer eyJhbGciOiJIUzI1NiIsInR5cCI6IkpXVCJ9.eyJpZFVzZXIiOjEsImlhdCI6MTY3MzM4OTcxNSwiZXhwIjoxNjczNDc2MTE1fQ.TjE7Iy4o9lQ6i_nNs9Lpu0m-g1yG9LkzsbnglAl6Yx4",
						"type": "text"
					}
				],
				"body": {
					"mode": "raw",
					"raw": "",
					"options": {
						"raw": {
							"language": "json"
						}
					}
				},
				"url": {
					"raw": "http://localhost:8080/exercises/1",
					"protocol": "http",
					"host": [
						"localhost"
					],
					"port": "8080",
					"path": [
						"exercises",
						"1"
					]
				}
			},
			"response": []
		}
	]
}